{"type": "scene", "properties": {"width": 100.0, "height": 106.15384615381059, "baseExtent": {"x": 720989.3103681487, "y": 4427282.708773401, "width": 251.7608776979614, "height": 267.2538547869772, "rotation": 0}, "zExaggeration": 1.0, "zShift": 0.0}, "layers": [{"type": "layer", "id": 0, "properties": {"name": "DSM", "clickable": true, "visible": true, "type": "dem", "shading": true}, "data": [{"type": "block", "layer": 0, "block": 0, "width": 100.0, "height": 106.15234375, "translate": [0.0, 0.0, 0.0], "zShift": 0.0, "zScale": 0.39720230130421785, "material": {"type": 0, "image": {"url": "./data/index/a0.png"}, "ds": 1}, "grid": {"width": 195, "height": 207, "url": "./data/index/a0.bin"}, "sides": {"mtl": {"type": 0, "c": 13417386}}}]}]}